{
  "nodes": [
    {
      "name": "L0N0",
      "layer": "input",
      "value": 0.05,
      "num": 0
    },
    {
      "name": "L0N1",
      "layer": "input",
      "value": 0.5,
      "num": 1
    },
    {
      "name": "L0N2",
      "layer": "input",
      "value": 0.9500000000000001,
      "num": 2
    },
    {
      "name": "L2N0",
      "layer": "relu",
      "value": 0.05,
      "num": 3
    },
    {
      "name": "L2N1",
      "layer": "relu",
      "value": 0.9411452807673357,
      "num": 4
    },
    {
      "name": "L2N2",
      "layer": "relu",
      "value": 0.06433806125581985,
      "num": 5
    },
    {
      "name": "L2N3",
      "layer": "relu",
      "value": 0.31423662844583594,
      "num": 6
    },
    {
      "name": "L2N4",
      "layer": "relu",
      "value": 0.07544867519806661,
      "num": 7
    },
    {
      "name": "L2N5",
      "layer": "relu",
      "value": 0.7593229389198916,
      "num": 8
    },
    {
      "name": "L2N6",
      "layer": "relu",
      "value": 0.9365646135710679,
      "num": 9
    },
    {
      "name": "L2N7",
      "layer": "relu",
      "value": 0.9500000000000001,
      "num": 10
    },
    {
      "name": "L4N0",
      "layer": "regression",
      "value": 0.5,
      "num": 11
    }
  ],
  "links": [
    {
      "source": 0,
      "target": 3,
      "value": 1.1,
      "v1": 0.05,
      "v2": 0.05,
      "idx": 0
    },
    {
      "source": 0,
      "target": 4,
      "value": 0.2088547192326644,
      "v1": 0.05,
      "v2": 0.9411452807673357,
      "idx": 1
    },
    {
      "source": 0,
      "target": 5,
      "value": 1.0856619387441802,
      "v1": 0.05,
      "v2": 0.06433806125581985,
      "idx": 2
    },
    {
      "source": 0,
      "target": 6,
      "value": 0.8357633715541641,
      "v1": 0.05,
      "v2": 0.31423662844583594,
      "idx": 3
    },
    {
      "source": 0,
      "target": 7,
      "value": 1.0745513248019334,
      "v1": 0.05,
      "v2": 0.07544867519806661,
      "idx": 4
    },
    {
      "source": 0,
      "target": 8,
      "value": 0.3906770610801086,
      "v1": 0.05,
      "v2": 0.7593229389198916,
      "idx": 5
    },
    {
      "source": 0,
      "target": 9,
      "value": 0.21343538642893223,
      "v1": 0.05,
      "v2": 0.9365646135710679,
      "idx": 6
    },
    {
      "source": 0,
      "target": 10,
      "value": 0.20000000000000007,
      "v1": 0.05,
      "v2": 0.9500000000000001,
      "idx": 7
    },
    {
      "source": 1,
      "target": 3,
      "value": 0.6500000000000001,
      "v1": 0.5,
      "v2": 0.05,
      "idx": 8
    },
    {
      "source": 1,
      "target": 4,
      "value": 0.6588547192326644,
      "v1": 0.5,
      "v2": 0.9411452807673357,
      "idx": 9
    },
    {
      "source": 1,
      "target": 5,
      "value": 0.66433806125582,
      "v1": 0.5,
      "v2": 0.06433806125581985,
      "idx": 10
    },
    {
      "source": 1,
      "target": 6,
      "value": 0.9142366284458361,
      "v1": 0.5,
      "v2": 0.31423662844583594,
      "idx": 11
    },
    {
      "source": 1,
      "target": 7,
      "value": 0.6754486751980667,
      "v1": 0.5,
      "v2": 0.07544867519806661,
      "idx": 12
    },
    {
      "source": 1,
      "target": 8,
      "value": 0.8406770610801085,
      "v1": 0.5,
      "v2": 0.7593229389198916,
      "idx": 13
    },
    {
      "source": 1,
      "target": 9,
      "value": 0.6634353864289322,
      "v1": 0.5,
      "v2": 0.9365646135710679,
      "idx": 14
    },
    {
      "source": 1,
      "target": 10,
      "value": 0.65,
      "v1": 0.5,
      "v2": 0.9500000000000001,
      "idx": 15
    },
    {
      "source": 2,
      "target": 3,
      "value": 0.20000000000000007,
      "v1": 0.9500000000000001,
      "v2": 0.05,
      "idx": 16
    },
    {
      "source": 2,
      "target": 4,
      "value": 1.0911452807673356,
      "v1": 0.9500000000000001,
      "v2": 0.9411452807673357,
      "idx": 17
    },
    {
      "source": 2,
      "target": 5,
      "value": 0.2143380612558199,
      "v1": 0.9500000000000001,
      "v2": 0.06433806125581985,
      "idx": 18
    },
    {
      "source": 2,
      "target": 6,
      "value": 0.4642366284458359,
      "v1": 0.9500000000000001,
      "v2": 0.31423662844583594,
      "idx": 19
    },
    {
      "source": 2,
      "target": 7,
      "value": 0.22544867519806666,
      "v1": 0.9500000000000001,
      "v2": 0.07544867519806661,
      "idx": 20
    },
    {
      "source": 2,
      "target": 8,
      "value": 0.9093229389198916,
      "v1": 0.9500000000000001,
      "v2": 0.7593229389198916,
      "idx": 21
    },
    {
      "source": 2,
      "target": 9,
      "value": 1.0865646135710678,
      "v1": 0.9500000000000001,
      "v2": 0.9365646135710679,
      "idx": 22
    },
    {
      "source": 2,
      "target": 10,
      "value": 1.1,
      "v1": 0.9500000000000001,
      "v2": 0.9500000000000001,
      "idx": 23
    },
    {
      "source": 3,
      "target": 11,
      "value": 0.6500000000000001,
      "v1": 0.05,
      "v2": 0.5,
      "idx": 24
    },
    {
      "source": 4,
      "target": 11,
      "value": 0.6588547192326644,
      "v1": 0.9411452807673357,
      "v2": 0.5,
      "idx": 25
    },
    {
      "source": 5,
      "target": 11,
      "value": 0.66433806125582,
      "v1": 0.06433806125581985,
      "v2": 0.5,
      "idx": 26
    },
    {
      "source": 6,
      "target": 11,
      "value": 0.9142366284458361,
      "v1": 0.31423662844583594,
      "v2": 0.5,
      "idx": 27
    },
    {
      "source": 7,
      "target": 11,
      "value": 0.6754486751980667,
      "v1": 0.07544867519806661,
      "v2": 0.5,
      "idx": 28
    },
    {
      "source": 8,
      "target": 11,
      "value": 0.8406770610801085,
      "v1": 0.7593229389198916,
      "v2": 0.5,
      "idx": 29
    },
    {
      "source": 9,
      "target": 11,
      "value": 0.6634353864289322,
      "v1": 0.9365646135710679,
      "v2": 0.5,
      "idx": 30
    },
    {
      "source": 10,
      "target": 11,
      "value": 0.65,
      "v1": 0.9500000000000001,
      "v2": 0.5,
      "idx": 31
    }
  ],
  "meta": [
    {
      "size": 10,
      "pos": 0.05
    },
    {
      "size": 11,
      "pos": 0.5
    },
    {
      "size": 12,
      "pos": 0.9500000000000001
    },
    {
      "size": 10,
      "pos": 0.05
    },
    {
      "size": 11,
      "pos": 0.9411452807673357
    },
    {
      "size": 12,
      "pos": 0.06433806125581985
    },
    {
      "size": 13,
      "pos": 0.31423662844583594
    },
    {
      "size": 14,
      "pos": 0.07544867519806661
    },
    {
      "size": 10,
      "pos": 0.7593229389198916
    },
    {
      "size": 11,
      "pos": 0.9365646135710679
    },
    {
      "size": 12,
      "pos": 0.9500000000000001
    },
    {
      "size": 10,
      "pos": 0.5
    }
  ],
  "opt": {
    "name": "xor_net",
    "node_scale": 10,
    "link_scale": 20,
    "link_opcty": 2
  }
}